update_linux/__init__.py
update_linux/__main__.py
update_linux-3.5.0.dist-info/licenses/LICENSE
update_linux-3.5.0.dist-info/METADATA
update_linux-3.5.0.dist-info/WHEEL
update_linux-3.5.0.dist-info/entry_points.txt
update_linux-3.5.0.dist-info/top_level.txt
update_linux-3.5.0.dist-info/RECORD
