Metadata-Version: 2.4
Name: update-linux
Version: 3.5.0
Summary: Command to automate the routine updating of packages and system upgrading for Unix systems.
Author-email: Barry Scott <barry@barrys-emacs.org>
License: Apache-2.0
Project-URL: Homepage, https://github.com/barry-scott/CLI-tools
Project-URL: Bug Tracker, https://github.com/barry-scott/CLI-tools/issues
Keywords: development
Classifier: Intended Audience :: End Users/Desktop
Classifier: Topic :: Utilities
Classifier: Environment :: Console
Classifier: Programming Language :: Python :: 3
Requires-Python: >=3.10
License-File: LICENSE
Requires-Dist: config-path
Requires-Dist: colour-text
Requires-Dist: ssh-wait
Dynamic: license-file
